{
  "$schema": "https://json-schema.org/draft/2020-12/schema",
  "title": "GRACE BELIEF_STATE",
  "type": "object",
  "required": ["anchor_id", "complexity", "assumptions", "risks", "failure_modes"],
  "properties": {
    "anchor_id": {
      "type": "string"
    },
    "complexity": {
      "type": "string",
      "enum": ["simple", "complex"]
    },
    "assumptions": {
      "type": "array",
      "items": {
        "type": "string"
      }
    },
    "risks": {
      "type": "array",
      "items": {
        "type": "string"
      }
    },
    "failure_modes": {
      "type": "array",
      "items": {
        "type": "string"
      }
    }
  },
  "additionalProperties": false
}
